abipy/__init__.py
abipy/abilab.py
abipy/rest.py
abipy/abio/__init__.py
abipy/abio/abivars.py
abipy/abio/abivars_db.py
abipy/abio/decorators.py
abipy/abio/enums.py
abipy/abio/factories.py
abipy/abio/input_tags.py
abipy/abio/inputs.py
abipy/abio/n1000multiples_primes.json
abipy/abio/outputs.py
abipy/abio/robots.py
abipy/abio/timer.py
abipy/abio/variable.py
abipy/abio/abivar_database/__init__.py
abipy/abio/abivar_database/variables.py
abipy/abio/abivar_database/variables_abinit.py
abipy/abio/abivar_database/variables_aim.py
abipy/abio/abivar_database/variables_anaddb.py
abipy/abio/abivar_database/variables_multibinit.py
abipy/abio/abivar_database/variables_optic.py
abipy/abio/tests/__init__.py
abipy/abio/tests/test_abivars.py
abipy/abio/tests/test_abivars_db.py
abipy/abio/tests/test_decorators.py
abipy/abio/tests/test_enums.py
abipy/abio/tests/test_factories.py
abipy/abio/tests/test_inputs.py
abipy/abio/tests/test_outputs.py
abipy/abio/tests/test_robots.py
abipy/abio/tests/test_variable.py
abipy/benchmarks/__init__.py
abipy/benchmarks/_dfpt_phonon_tio2.py
abipy/benchmarks/_runemall.py
abipy/benchmarks/_string5.py
abipy/benchmarks/bse_haydock.py
abipy/benchmarks/dfpt_autoparal_phonon.py
abipy/benchmarks/dfpt_ddk.py
abipy/benchmarks/dfpt_phonon.py
abipy/benchmarks/eph_al.py
abipy/benchmarks/gs_au108.py
abipy/benchmarks/gs_autoparal.py
abipy/benchmarks/gs_febio3.py
abipy/benchmarks/gs_istwfk.py
abipy/benchmarks/gs_kpara.py
abipy/benchmarks/gs_mpifft.py
abipy/benchmarks/gs_paralkgb.py
abipy/benchmarks/gs_pureomp.py
abipy/benchmarks/gs_ti256.py
abipy/benchmarks/gs_uo2.py
abipy/benchmarks/gs_useylm.py
abipy/benchmarks/gsio_paralkgb.py
abipy/benchmarks/moldyn1.py
abipy/benchmarks/moldyn5.py
abipy/benchmarks/rpa_optic.py
abipy/benchmarks/scr_hilbert.py
abipy/benchmarks/scr_rpa.py
abipy/benchmarks/sigma_cd.py
abipy/benchmarks/sigma_ppm.py
abipy/benchmarks/test_scripts.py
abipy/core/__init__.py
abipy/core/abinit_units.py
abipy/core/atom.py
abipy/core/fields.py
abipy-0.9.8.dist-info/LICENSE
abipy-0.9.8.dist-info/METADATA
abipy-0.9.8.dist-info/WHEEL
abipy-0.9.8.dist-info/top_level.txt
abipy-0.9.8.dist-info/RECORD
