Metadata-Version: 2.1
Name: abipy
Version: 0.9.8
Summary: Python package to automate ABINIT calculations and analyze the results.
Home-page: https://github.com/abinit/abipy
Download-URL: https://github.com/abinit/abipy
Author: M. Giantomassi and the AbiPy group
Author-email: matteo.giantomassi@uclouvain.be
Maintainer: Matteo Giantomassi
Maintainer-email: matteo.giantomassi@uclouvain.be
License: GPL
Keywords: ABINIT,ab-initio,density-function-theory,first-principles,electronic-structure,pymatgen
Platform: Linux
Platform: darwin
Classifier: Programming Language :: Python :: 3.8
Classifier: Programming Language :: Python :: 3.9
Classifier: Programming Language :: Python :: 3.10
Classifier: Programming Language :: Python :: 3.11
Classifier: Programming Language :: Python :: 3.12
Classifier: Development Status :: 4 - Beta
Classifier: Intended Audience :: Science/Research
Classifier: License :: OSI Approved :: GNU General Public License v2 (GPLv2)
Classifier: Operating System :: OS Independent
Classifier: Topic :: Scientific/Engineering :: Information Analysis
Classifier: Topic :: Scientific/Engineering :: Physics
Classifier: Topic :: Scientific/Engineering :: Chemistry
Classifier: Topic :: Software Development :: Libraries :: Python Modules
License-File: LICENSE
Requires-Dist: monty
Requires-Dist: packaging
Requires-Dist: tabulate
Requires-Dist: apscheduler <=3.10.4
Requires-Dist: pydispatcher >=2.0.5
Requires-Dist: tqdm
Requires-Dist: pyyaml >=3.11
Requires-Dist: pandas
Requires-Dist: numpy <2.0.0
Requires-Dist: scipy
Requires-Dist: spglib
Requires-Dist: pymatgen >=2022.0.14
Requires-Dist: netCDF4
Requires-Dist: matplotlib
Requires-Dist: seaborn
Requires-Dist: plotly
Requires-Dist: ipython
Requires-Dist: chart-studio
Requires-Dist: click
Requires-Dist: phonopy
Requires-Dist: ase
